helpme/__init__.py
helpme/helpme.py
dorara-1.0.0.dist-info/LICENSE
dorara-1.0.0.dist-info/METADATA
dorara-1.0.0.dist-info/WHEEL
dorara-1.0.0.dist-info/entry_points.txt
dorara-1.0.0.dist-info/top_level.txt
dorara-1.0.0.dist-info/RECORD
